evorl/__init__.py
evorl/agents/__init__.py
evorl/agents/base.py
evorl/agents/dqn.py
evorl/agents/ppo.py
evorl/agents/utils.py
evorl/environments/__init__.py
evorl/environments/wrappers.py
evorl/evolution/__init__.py
evorl/evolution/population.py
evorl/evolution/strategies.py
evorl-2.0.0.dist-info/LICENSE
evorl-2.0.0.dist-info/METADATA
evorl-2.0.0.dist-info/WHEEL
evorl-2.0.0.dist-info/top_level.txt
evorl-2.0.0.dist-info/RECORD
