Metadata-Version: 2.2
Name: evorl
Version: 2.0.0
Summary: An evolutionary reinforcement learning framework
Home-page: https://github.com/zhangalex1/evorl
Author: Alex Zhang
Author-email: zhangalex1237@gmail.com
Project-URL: Documentation, https://evorl.ai
Project-URL: Bug Tracker, https://github.com/zhangalex1/evorl/issues
Project-URL: Source Code, https://github.com/zhangalex1/evorl
Keywords: reinforcement-learning,evolutionary-algorithms,deep-learning,pytorch,rl
Classifier: Development Status :: 4 - Beta
Classifier: Intended Audience :: Science/Research
Classifier: License :: OSI Approved :: MIT License
Classifier: Programming Language :: Python :: 3
Classifier: Programming Language :: Python :: 3.8
Classifier: Programming Language :: Python :: 3.9
Classifier: Programming Language :: Python :: 3.10
Classifier: Topic :: Scientific/Engineering :: Artificial Intelligence
Requires-Python: >=3.8
License-File: LICENSE
Requires-Dist: torch>=1.8.0
Requires-Dist: numpy>=1.19.0
Requires-Dist: gymnasium>=0.26.0
Requires-Dist: matplotlib>=3.3.0
Requires-Dist: seaborn>=0.11.0
Provides-Extra: dev
Requires-Dist: pytest>=6.0; extra == "dev"
Requires-Dist: pytest-cov>=2.0; extra == "dev"
Requires-Dist: black>=22.0; extra == "dev"
Requires-Dist: isort>=5.0; extra == "dev"
Requires-Dist: flake8>=3.9; extra == "dev"
Requires-Dist: mypy>=0.9; extra == "dev"
Provides-Extra: docs
Requires-Dist: sphinx>=4.0; extra == "docs"
Requires-Dist: sphinx-rtd-theme>=1.0; extra == "docs"
Dynamic: author
Dynamic: author-email
Dynamic: classifier
Dynamic: description
Dynamic: description-content-type
Dynamic: home-page
Dynamic: keywords
Dynamic: project-url
Dynamic: provides-extra
Dynamic: requires-dist
Dynamic: requires-python
Dynamic: summary
